code_converters/binary_to_gray.v
module binary_to_gray(input [3:0]b, output [3:0]g);
assign g[3] = b[3];
assign g[2] =b[3] ^ b[2];
assign g[1] =b[2] ^ b[1];
assign g[0] =b[1] ^ b[0];
endmodule
//single line code?assign g = b ^ (b >> 1);

code_converters/binary_to_gray_tb.v
`include "./binary_to_gray.v"
module binary_to_gray_tb;
    reg [3:0] b;
    wire [3:0] g;
    integer i;
    binary_to_gray dut(
        .b(b),
        .g(g)
    );
    initial begin
        $dumpfile("binary_to_gray.vcd");
        $dumpvars(0, binary_to_gray_tb);
        //integer i;
        $display("time \t decimal \t binary number \t gray code");
        $display("---------------------------------------------------");
        for(i=0;i<16;i=i+1) begin
            b=i;
            #5;
            //binary_to_gray(b,g);
            
            $display("%0tns \t  %0d \t \t  %b  \t    %b", $time, b,b,g);
            #5;
            
        end
        $display("---------------------------------------------------");
        $display("done");
    end
endmodule

code_converters/binary_to_gray.vcd
$date
	Sun Jul 19 16:51:01 2026
$end
$version
	Icarus Verilog
$end
$timescale
	1s
$end
$scope module binary_to_gray_tb $end
$var wire 4 ! g [3:0] $end
$var reg 4 " b [3:0] $end
$var integer 32 # i [31:0] $end
$scope module dut $end
$var wire 4 $ b [3:0] $end
$var wire 4 % g [3:0] $end
$upscope $end
$upscope $end
$enddefinitions $end
$comment Show the parameter values. $end
$dumpall
$end
#0
$dumpvars
b0 %
b0 $
b0 #
b0 "
b0 !
$end
#10
b1 !
b1 %
b1 "
b1 $
b1 #
#20
b11 !
b11 %
b10 "
b10 $
b10 #
#30
b10 !
b10 %
b11 "
b11 $
b11 #
#40
b110 !
b110 %
b100 "
b100 $
b100 #
#50
b111 !
b111 %
b101 "
b101 $
b101 #
#60
b101 !
b101 %
b110 "
b110 $
b110 #
#70
b100 !
b100 %
b111 "
b111 $
b111 #
#80
b1100 !
b1100 %
b1000 "
b1000 $
b1000 #
#90
b1101 !
b1101 %
b1001 "
b1001 $
b1001 #
#100
b1111 !
b1111 %
b1010 "
b1010 $
b1010 #
#110
b1110 !
b1110 %
b1011 "
b1011 $
b1011 #
#120
b1010 !
b1010 %
b1100 "
b1100 $
b1100 #
#130
b1011 !
b1011 %
b1101 "
b1101 $
b1101 #
#140
b1001 !
b1001 %
b1110 "
b1110 $
b1110 #
#150
b1000 !
b1000 %
b1111 "
b1111 $
b1111 #
#160
b10000 #
