code_converters/gray_to_binary.v
module gray_to_binary(input [3:0] g, output [3:0] b);
    assign b[3] = g[3];
    assign b[2] = b[3] ^ g[2];
    assign b[1] = b[2] ^ g[1];
    assign b[0] = b[1] ^ g[0];



endmodule

code_converters/gray_to_binary_tb.v
`include "./gray_to_binary.v"
module gray_to_binary_tb;
    wire [3:0] b;
    reg [3:0] g;
    integer i;
    gray_to_binary dut (
        .g(g),
        .b(b)
    );
    initial begin
        $dumpfile("gray_to_binary.vcd");
        $dumpvars(0, gray_to_binary_tb);
        //integer i;
        $display("time \t graycode \t binary number ");
        $display("---------------------------------------------------");
        for(i=0;i<16;i=i+1) begin
            g=i;
            #5;
            //binary_to_gray(b,g);
            
            $display("%0tns \t  \t  %b  \t    %b", $time, g,b);
            #5;
            
        end
        $display("---------------------------------------------------");
        $display("done");
    end
endmodule

code_converters/gray_to_binary.vcd
$date
	Sun Jul 19 16:54:58 2026
$end
$version
	Icarus Verilog
$end
$timescale
	1s
$end
$scope module gray_to_binary_tb $end
$var wire 4 ! b [3:0] $end
$var reg 4 " g [3:0] $end
$var integer 32 # i [31:0] $end
$scope module dut $end
$var wire 4 $ g [3:0] $end
$var wire 4 % b [3:0] $end
$upscope $end
$upscope $end
$enddefinitions $end
$comment Show the parameter values. $end
$dumpall
$end
#0
$dumpvars
b0 %
b0 $
b0 #
b0 "
b0 !
$end
#10
b1 !
b1 %
b1 "
b1 $
b1 #
#20
b11 !
b11 %
b10 "
b10 $
b10 #
#30
b10 !
b10 %
b11 "
b11 $
b11 #
#40
b111 !
b111 %
b100 "
b100 $
b100 #
#50
b110 !
b110 %
b101 "
b101 $
b101 #
#60
b100 !
b100 %
b110 "
b110 $
b110 #
#70
b101 !
b101 %
b111 "
b111 $
b111 #
#80
b1111 !
b1111 %
b1000 "
b1000 $
b1000 #
#90
b1110 !
b1110 %
b1001 "
b1001 $
b1001 #
#100
b1100 !
b1100 %
b1010 "
b1010 $
b1010 #
#110
b1101 !
b1101 %
b1011 "
b1011 $
b1011 #
#120
b1000 !
b1000 %
b1100 "
b1100 $
b1100 #
#130
b1001 !
b1001 %
b1101 "
b1101 $
b1101 #
#140
b1011 !
b1011 %
b1110 "
b1110 $
b1110 #
#150
b1010 !
b1010 %
b1111 "
b1111 $
b1111 #
#160
b10000 #
