code_converters/binary_to_gray.v
module binary_to_gray(input [3:0]b, output [3:0]g);
assign g[3] = b[3];
assign g[2] =b[3] ^ b[2];
assign g[1] =b[2] ^ b[1];
assign g[0] =b[1] ^ b[0];
endmodule
//single line code?assign g = b ^ (b >> 1);

code_converters/binary_to_excess3_to_gray.v
`include "./binary_to_gray.v"

module binary_to_excess3_to_gray (
    input wire [3:0] binary_in,    // Your starting raw binary number (e.g., 4'b0101)
    output wire [3:0] gray_out     // Final Gray code output
);

    wire [3:0] excess3_val;        // Internal wire to hold the intermediate Excess-3 value

    // Step 1: Add 3 to the input binary number to generate the Excess-3 representation
    assign excess3_val = binary_in + 4'b0011;

    // Step 2: Instantiate your existing binary_to_gray module 
    // to convert that Excess-3 bit pattern directly into Gray code
    binary_to_gray u_b2g (
        .b(excess3_val),   // Feed the intermediate value here
        .g(gray_out)        // Connect to final top-level output
    );

endmodule

code_converters/binary_to_excess3_to_gray_tb.v
`include "./binary_to_excess3_to_gray.v"
`timescale 1ns/1ps
module binary_to_excess3_to_gray_tb;
    reg [3:0] binary_in;    // Stimulus: Raw binary input
    wire [3:0] gray_out;    // Monitor: Output from the pipeline
    integer i;

    // Instantiate the Top-Level Pipeline Module
    binary_to_excess3_to_gray dut (
        .binary_in(binary_in),
        .gray_out(gray_out)
    );

    initial begin
        // Setup VCD file generation for GTKWave
        $dumpfile("pipeline_sim.vcd");
        $dumpvars(0, binary_to_excess3_to_gray_tb);
        
        $display("Time \t Input (Binary) \t Expected Excess-3 \t \t Output (Gray)");
        $display("--------------------------------------------------------------------------");
        
        // Loop through decimal values 0 to 9
        for(i = 0; i < 10; i = i + 1) begin
            binary_in = i;
            #10; // Wait 10ns for logic propagation and viewing clarity
            
            $display("%0tns \t %b (%0d) \t\t %b (%0d) \t\t\t %b", 
                     $time, binary_in, binary_in, (binary_in + 4'b0011), (binary_in + 3), gray_out);
        end
        
        $display("--------------------------------------------------------------------------");
        $display("Simulation complete successfully.");
        $finish;
    end

endmodule

code_converters/pipeline_sim.vcd
$date
	Sun Jul 19 16:59:56 2026
$end
$version
	Icarus Verilog
$end
$timescale
	1ps
$end
$scope module binary_to_excess3_to_gray_tb $end
$var wire 4 ! gray_out [3:0] $end
$var reg 4 " binary_in [3:0] $end
$var integer 32 # i [31:0] $end
$scope module dut $end
$var wire 4 $ binary_in [3:0] $end
$var wire 4 % gray_out [3:0] $end
$var wire 4 & excess3_val [3:0] $end
$scope module u_b2g $end
$var wire 4 ' b [3:0] $end
$var wire 4 ( g [3:0] $end
$upscope $end
$upscope $end
$upscope $end
$enddefinitions $end
$comment Show the parameter values. $end
$dumpall
$end
#0
$dumpvars
b10 (
b11 '
b11 &
b10 %
b0 $
b0 #
b0 "
b10 !
$end
#10000
b110 !
b110 %
b110 (
b100 &
b100 '
b1 "
b1 $
b1 #
#20000
b111 !
b111 %
b111 (
b101 &
b101 '
b10 "
b10 $
b10 #
#30000
b101 !
b101 %
b101 (
b110 &
b110 '
b11 "
b11 $
b11 #
#40000
b100 !
b100 %
b100 (
b111 &
b111 '
b100 "
b100 $
b100 #
#50000
b1100 !
b1100 %
b1100 (
b1000 &
b1000 '
b101 "
b101 $
b101 #
#60000
b1101 !
b1101 %
b1101 (
b1001 &
b1001 '
b110 "
b110 $
b110 #
#70000
b1111 !
b1111 %
b1111 (
b1010 &
b1010 '
b111 "
b111 $
b111 #
#80000
b1110 !
b1110 %
b1110 (
b1011 &
b1011 '
b1000 "
b1000 $
b1000 #
#90000
b1010 !
b1010 %
b1010 (
b1100 &
b1100 '
b1001 "
b1001 $
b1001 #
#100000
b1010 #
