mux_2to1_df/mux_2to1_df.v
module mux_2to1_df(
    input a,b,sel,
    output out
);
    //data flow method:- we ca directly assig the circuit equation
    assign out=(a&~sel) | (b&sel);


endmodule

mux_2to1_df/tb_mux_2to1.v
`timescale 1ns/1ps
module tb_mux_2to1_df;
    reg a,b,sel;
    wire out;
    mux_2to1_df uut(
        .a(a),
        .b(b),
        .sel(sel),
        .out(out)
    );
    initial begin
        $dumpfile("mux_2to1_df_sim.vcd");
        $dumpvars(0,tb_mux_2to1_df);
        $display("Sel A B | Out");
        $monitor("%b   %b %b |   %b", sel, a, b, out);

        // Apply the 8 possible combinations
        {sel, a, b} = 3'b000; #10;
        {sel, a, b} = 3'b001; #10;
        {sel, a, b} = 3'b010; #10;
        {sel, a, b} = 3'b011; #10;
        {sel, a, b} = 3'b100; #10;
        {sel, a, b} = 3'b101; #10;
        {sel, a, b} = 3'b110; #10;
        {sel, a, b} = 3'b111; #10;
        $finish;

    end
endmodule

mux_2to1_df/mux_2to1_df_sim.vcd
$date
	Sat Apr 25 18:25:40 2026
$end
$version
	Icarus Verilog
$end
$timescale
	1ps
$end
$scope module tb_mux_2to1_df $end
$var wire 1 ! out $end
$var reg 1 " a $end
$var reg 1 # b $end
$var reg 1 $ sel $end
$scope module uut $end
$var wire 1 " a $end
$var wire 1 # b $end
$var wire 1 ! out $end
$var wire 1 $ sel $end
$upscope $end
$upscope $end
$enddefinitions $end
$comment Show the parameter values. $end
$dumpall
$end
#0
$dumpvars
0$
0#
0"
0!
$end
#10000
1#
#20000
1!
1"
0#
#30000
1#
#40000
0!
1$
0"
0#
#50000
1!
1#
#60000
0!
1"
0#
#70000
1!
1#
