mux_2to1_bh/mux_2to1_bh.v
module mux_2to1_bh(
    input a,b,sel,
    output reg out
);
    always @(*) begin
        if (sel==1'b1)
            out=b;

        else
            out=a;
    end
endmodule

mux_2to1_bh/tb_mux_2to1_bh.v
`timescale 1ns/1ps
module tb_mux_2to1_bh;
    reg a,b,sel;
    wire out;
    mux_2to1_bh uut(
        .a(a),
        .b(b),
        .sel(sel),
        .out(out)
    );
    initial begin
        $dumpfile("mux_2to1_bh_sim.vcd");
        $dumpvars(0,tb_mux_2to1_bh);
        $display("Sel A B | Out");
        $monitor("%b   %b %b |   %b", sel, a, b, out);

        // Apply the 8 possible combinations
        {sel, a, b} = 3'b000; #10;
        {sel, a, b} = 3'b001; #10;
        {sel, a, b} = 3'b010; #10;
        {sel, a, b} = 3'b011; #10;
        {sel, a, b} = 3'b100; #10;
        {sel, a, b} = 3'b101; #10;
        {sel, a, b} = 3'b110; #10;
        {sel, a, b} = 3'b111; #10;
        $finish;

    end
endmodule

mux_2to1_bh/mux_2to1_bh_sim.vcd
$date
	Sun Apr 26 11:41:22 2026
$end
$version
	Icarus Verilog
$end
$timescale
	1ps
$end
$scope module tb_mux_2to1_bh $end
$var wire 1 ! out $end
$var reg 1 " a $end
$var reg 1 # b $end
$var reg 1 $ sel $end
$scope module uut $end
$var wire 1 " a $end
$var wire 1 # b $end
$var wire 1 $ sel $end
$var reg 1 ! out $end
$upscope $end
$upscope $end
$enddefinitions $end
$comment Show the parameter values. $end
$dumpall
$end
#0
$dumpvars
0$
0#
0"
0!
$end
#10000
1#
#20000
1!
1"
0#
#30000
1#
#40000
0!
1$
0"
0#
#50000
1!
1#
#60000
0!
1"
0#
#70000
1!
1#
