counters_using_flip_flops/sr_flip_flop.v
module sr_flip_flop (
    input clk,
    input rst,
    input s,
    input r,
    output reg q,
    output  q_bar
);

    assign q_bar = ~q;

    always @(posedge clk or posedge rst) begin
        if (rst) begin
            q <= 1'b0;      // Asynchronous clear
        end else begin
            case ({s, r})
                2'b00: q <= q;    // Hold state
                2'b01: q <= 1'b0; // Reset state
                2'b10: q <= 1'b1; // Set state
                2'b11: q <= 1'bx; // Invalid state (Don't care / undefined behavior)
            endcase
        end
    end

endmodule

counters_using_flip_flops/d_flip_flop.v
`include "sr_flip_flop.v"
module d_flip_flop(
    input clk,
    input rst,
    input d,
    output q,
    output  q_bar
    );
    wire d_bar;
    assign d_bar = ~d;
    sr_flip_flop sr1 (clk, rst, d, d_bar, q, q_bar); // calling instance of sr module with conditions to get d flip flop directly.
endmodule

counters_using_flip_flops/d_flip_flop_tb.v
`timescale 1ns/1ps
`include "d_flip_flop.v"

module d_flip_flop_tb;
    reg clk;
    reg rst;
    reg d;
    wire q;
    wire q_bar;

    // Instantiate your D Flip-Flop module
    d_flip_flop dut (
        .clk(clk),
        .rst(rst),
        .d(d),
        .q(q),
        .q_bar(q_bar)
    );

    // Generate Clock: 10ns period (toggles every 5ns)
    always #5 clk = ~clk;
initial begin
        $dumpfile("d_flip_flop_sim.vcd");
        $dumpvars(0, d_flip_flop_tb);

        // Initialize inputs
        clk = 0;
        rst = 1; // Assert reset immediately
        d = 0;   // Q is forced to 0
        
        // Toggle D while reset is active to prove it's ignored
        #3 d = 1; // At 3ns: D goes high, but Q must stay 0!
        #5 d = 0; // At 8ns (3+5): D goes low, Q must stay 0!
        
        #4 rst = 0; // At 12ns (8+4): De-assert reset
        
        // Normal operation continues...
        #5 d = 1;  // At 17ns: Set D high for the upcoming 25ns clock edge
        #10;     
        d = 0;
        #10;
        
        $finish;
    end
endmodule

counters_using_flip_flops/d_flip_flop_sim.vcd
$date
	Sat Jul 18 16:30:48 2026
$end
$version
	Icarus Verilog
$end
$timescale
	1ps
$end
$scope module d_flip_flop_tb $end
$var wire 1 ! q_bar $end
$var wire 1 " q $end
$var reg 1 # clk $end
$var reg 1 $ d $end
$var reg 1 % rst $end
$scope module dut $end
$var wire 1 # clk $end
$var wire 1 $ d $end
$var wire 1 & d_bar $end
$var wire 1 % rst $end
$var wire 1 ! q_bar $end
$var wire 1 " q $end
$scope module sr1 $end
$var wire 1 # clk $end
$var wire 1 ! q_bar $end
$var wire 1 & r $end
$var wire 1 % rst $end
$var wire 1 $ s $end
$var reg 1 " q $end
$upscope $end
$upscope $end
$upscope $end
$enddefinitions $end
$comment Show the parameter values. $end
$dumpall
$end
#0
$dumpvars
1&
1%
0$
0#
0"
1!
$end
#3000
0&
1$
#5000
1#
#8000
1&
0$
#10000
0#
#12000
0%
#15000
1#
#17000
0&
1$
#20000
0#
#25000
0!
1"
1#
#27000
1&
0$
#30000
0#
#35000
1!
0"
1#
