counters_using_flip_flops/mod6_counter_behavioural.v
module mod6_counter_behavioural(
    input wire clk,
    input wire rst,
    output reg [2:0] q
);

always @(posedge clk or posedge rst) begin
    if(rst) begin
        q <=3'b000;
    end
    else begin
        if(q == 3'b101) begin
            q <= 3'b000;
        end
        else begin
            q <= q + 1'b1;
        end
    end
end

endmodule

counters_using_flip_flops/mod6_counter_behavioural_tb.v
`timescale 1ns/1ps
`include "mod6_counter_behavioural.v"

module mod6_counter_behavioural_tb;
    reg clk;
    reg rst;
    wire [2:0] q;

    // Instantiate the behavioral Mod-6 counter
    mod6_counter_behavioural dut (
        .clk(clk),
        .rst(rst),
        .q(q)
    );

    // Generate Clock: 10ns period (toggles every 5ns)
    always #5 clk = ~clk;

    initial begin
        // Setup GTKWave dump files
        $dumpfile("mod6_behavioural_sim.vcd");
        $dumpvars(0, mod6_counter_behavioural_tb);

        // Initialize and apply reset
        clk = 0;
        rst = 1;
        #12; // Release reset at 12ns
        
        rst = 0;

        // Run long enough to see the sequence multiple times
        #140;

        $display("Behavioral Mod-6 counter simulation complete!");
        $finish;
    end
endmodule

counters_using_flip_flops/mod6_behavioural_sim.vcd
$date
	Sat Jul 18 20:15:52 2026
$end
$version
	Icarus Verilog
$end
$timescale
	1ps
$end
$scope module mod6_counter_behavioural_tb $end
$var wire 3 ! q [2:0] $end
$var reg 1 " clk $end
$var reg 1 # rst $end
$scope module dut $end
$var wire 1 " clk $end
$var wire 1 # rst $end
$var reg 3 $ q [2:0] $end
$upscope $end
$upscope $end
$enddefinitions $end
$comment Show the parameter values. $end
$dumpall
$end
#0
$dumpvars
b0 $
1#
0"
b0 !
$end
#5000
1"
#10000
0"
#12000
0#
#15000
b1 !
b1 $
1"
#20000
0"
#25000
b10 !
b10 $
1"
#30000
0"
#35000
b11 !
b11 $
1"
#40000
0"
#45000
b100 !
b100 $
1"
#50000
0"
#55000
b101 !
b101 $
1"
#60000
0"
#65000
b0 !
b0 $
1"
#70000
0"
#75000
b1 !
b1 $
1"
#80000
0"
#85000
b10 !
b10 $
1"
#90000
0"
#95000
b11 !
b11 $
1"
#100000
0"
#105000
b100 !
b100 $
1"
#110000
0"
#115000
b101 !
b101 $
1"
#120000
0"
#125000
b0 !
b0 $
1"
#130000
0"
#135000
b1 !
b1 $
1"
#140000
0"
#145000
b10 !
b10 $
1"
