counters_using_flip_flops/sr_flip_flop.v
module sr_flip_flop (
    input clk,
    input rst,
    input s,
    input r,
    output reg q,
    output  q_bar
);

    assign q_bar = ~q;

    always @(posedge clk or posedge rst) begin
        if (rst) begin
            q <= 1'b0;      // Asynchronous clear
        end else begin
            case ({s, r})
                2'b00: q <= q;    // Hold state
                2'b01: q <= 1'b0; // Reset state
                2'b10: q <= 1'b1; // Set state
                2'b11: q <= 1'bx; // Invalid state (Don't care / undefined behavior)
            endcase
        end
    end

endmodule

counters_using_flip_flops/d_flip_flop.v
`include "sr_flip_flop.v"
module d_flip_flop(
    input clk,
    input rst,
    input d,
    output q,
    output  q_bar
    );
    wire d_bar;
    assign d_bar = ~d;
    sr_flip_flop sr1 (clk, rst, d, d_bar, q, q_bar); // calling instance of sr module with conditions to get d flip flop directly.
endmodule

counters_using_flip_flops/mod6_counter_structural.v
`include "d_flip_flop.v"
module mod6_counter(
    input clk,
    input rst,

    output q2,
    output q2_bar,
    output q1,
    output q1_bar,
    output q0,
    output q0_bar
    
);
wire d2,d1,d0;
wire y1,y2;
wire y3,y4;



    assign d0 = q0_bar; //LSB

    and g1 (y1,q1,q0_bar);
    and g2 (y2,q2_bar,q1_bar,q0);
    or  g3 (d1,y1,y2);//d1

    and g4 (y3,q1,q0);
    and g5 (y4,q2,q0_bar);
    or  g6 (d2,y3,y4);//msb


d_flip_flop dc(clk, rst, d2, q2, q2_bar);//msb
d_flip_flop db(clk, rst, d1, q1, q1_bar);
d_flip_flop da(clk, rst, d0, q0, q0_bar);//lsb

endmodule

counters_using_flip_flops/mod6_counter_structural_tb.v
`timescale 1ns/1ps
`include "mod6_counter_structural.v"

module mod6_counter_tb;
    reg clk;
    reg rst;
    wire q2, q1, q0;
    wire q2_bar, q1_bar, q0_bar;

    // Instantiate your optimized structural Mod-6 counter
    mod6_counter dut (
        .clk(clk),
        .rst(rst),
        .q2(q2),
        .q2_bar(q2_bar),
        .q1(q1),
        .q1_bar(q1_bar),
        .q0(q0),
        .q0_bar(q0_bar)
    );

    // Generate Clock: 10ns period (toggles every 5ns)
    always #5 clk = ~clk;

    initial begin
        // Setup GTKWave dump files
        $dumpfile("mod6_structural_sim.vcd");
        $dumpvars(0, mod6_counter_tb);

        // Initialize and apply reset
        clk = 0;
        rst = 1;
        #12; // Release reset at 12ns (safely away from the 10ns clock edge)
        
        rst = 0;

        // Run long enough to watch the counter step 0 -> 1 -> 2 -> 3 -> 4 -> 5 -> 0 multiple times
        #140;

        $display("Structural Mod-6 counter simulation complete!");
        $finish;
    end
endmodule

counters_using_flip_flops/mod6_structural_sim.vcd
$date
	Sat Jul 18 19:47:14 2026
$end
$version
	Icarus Verilog
$end
$timescale
	1ps
$end
$scope module mod6_counter_tb $end
$var wire 1 ! q2_bar $end
$var wire 1 " q2 $end
$var wire 1 # q1_bar $end
$var wire 1 $ q1 $end
$var wire 1 % q0_bar $end
$var wire 1 & q0 $end
$var reg 1 ' clk $end
$var reg 1 ( rst $end
$scope module dut $end
$var wire 1 ' clk $end
$var wire 1 ) d0 $end
$var wire 1 * d1 $end
$var wire 1 + d2 $end
$var wire 1 ( rst $end
$var wire 1 , y1 $end
$var wire 1 - y2 $end
$var wire 1 . y3 $end
$var wire 1 / y4 $end
$var wire 1 ! q2_bar $end
$var wire 1 " q2 $end
$var wire 1 # q1_bar $end
$var wire 1 $ q1 $end
$var wire 1 % q0_bar $end
$var wire 1 & q0 $end
$scope module da $end
$var wire 1 ' clk $end
$var wire 1 ) d $end
$var wire 1 0 d_bar $end
$var wire 1 ( rst $end
$var wire 1 % q_bar $end
$var wire 1 & q $end
$scope module sr1 $end
$var wire 1 ' clk $end
$var wire 1 % q_bar $end
$var wire 1 0 r $end
$var wire 1 ( rst $end
$var wire 1 ) s $end
$var reg 1 & q $end
$upscope $end
$upscope $end
$scope module db $end
$var wire 1 ' clk $end
$var wire 1 * d $end
$var wire 1 1 d_bar $end
$var wire 1 ( rst $end
$var wire 1 # q_bar $end
$var wire 1 $ q $end
$scope module sr1 $end
$var wire 1 ' clk $end
$var wire 1 # q_bar $end
$var wire 1 1 r $end
$var wire 1 ( rst $end
$var wire 1 * s $end
$var reg 1 $ q $end
$upscope $end
$upscope $end
$scope module dc $end
$var wire 1 ' clk $end
$var wire 1 + d $end
$var wire 1 2 d_bar $end
$var wire 1 ( rst $end
$var wire 1 ! q_bar $end
$var wire 1 " q $end
$scope module sr1 $end
$var wire 1 ' clk $end
$var wire 1 ! q_bar $end
$var wire 1 2 r $end
$var wire 1 ( rst $end
$var wire 1 + s $end
$var reg 1 " q $end
$upscope $end
$upscope $end
$upscope $end
$upscope $end
$enddefinitions $end
$comment Show the parameter values. $end
$dumpall
$end
#0
$dumpvars
12
11
00
0/
0.
0-
0,
0+
0*
1)
1(
0'
0&
1%
0$
1#
0"
1!
$end
#5000
1'
#10000
0'
#12000
0(
#15000
01
10
1*
0)
0%
1-
1&
1'
#20000
0'
#25000
01
1,
00
1*
1)
1%
0-
0#
0&
1$
1'
#30000
0'
#35000
11
0*
02
0,
10
1+
0)
0%
1.
1&
1'
#40000
0'
#45000
02
1/
00
1+
1)
1%
1#
0.
0!
0&
0$
1"
1'
#50000
0'
#55000
12
0+
0/
10
0)
0%
1&
1'
#60000
0'
#65000
00
1)
1%
1!
0&
0"
1'
#70000
0'
#75000
01
10
1*
0)
0%
1-
1&
1'
#80000
0'
#85000
01
1,
00
1*
1)
1%
0-
0#
0&
1$
1'
#90000
0'
#95000
11
0*
02
0,
10
1+
0)
0%
1.
1&
1'
#100000
0'
#105000
02
1/
00
1+
1)
1%
1#
0.
0!
0&
0$
1"
1'
#110000
0'
#115000
12
0+
0/
10
0)
0%
1&
1'
#120000
0'
#125000
00
1)
1%
1!
0&
0"
1'
#130000
0'
#135000
01
10
1*
0)
0%
1-
1&
1'
#140000
0'
#145000
01
1,
00
1*
1)
1%
0-
0#
0&
1$
1'
