full_adder/full_adder.v
module full_adder(
    input a,
    input b,
    input cin,
    output sum,
    output cout
);
    assign sum=a^b^cin;
    assign cout=(a&b) | (cin&(a^b));



endmodule

full_adder/tb_full_adder.v

`timescale 1ns/1ps
module tb_full_adder;
    reg a, b,cin;
    wire sum, cout;
    full_adder uut ( 
        .a(a),
        .b(b),
        .sum(sum),
        .cout(cout),
        .cin(cin)

    );
    initial begin
        $dumpfile("full_adder_sim.vcd");
        $dumpvars(0,tb_full_adder);
        //$monitor("Time=%0t | a=%b b=%b | S=%b c=%b",$time,$a,$b,$sum,$carry);
        a=0;b=0;cin=0;#1;
        a=0;b=0;cin=1;#1;
        a=0;b=1;cin=0;#1;
        a=0;b=1;cin=1;#1;
        a=1;b=0;cin=0;#1;
        a=1;b=0;cin=1;#1;
        a=1;b=1;cin=0;#1;
        a=1;b=1;cin=1;#1;
        
        $finish;
    end
endmodule

full_adder/full_adder_sim.vcd
$date
	Fri Apr 24 17:38:36 2026
$end
$version
	Icarus Verilog
$end
$timescale
	1ps
$end
$scope module tb_full_adder $end
$var wire 1 ! sum $end
$var wire 1 " cout $end
$var reg 1 # a $end
$var reg 1 $ b $end
$var reg 1 % cin $end
$scope module uut $end
$var wire 1 # a $end
$var wire 1 $ b $end
$var wire 1 % cin $end
$var wire 1 " cout $end
$var wire 1 ! sum $end
$upscope $end
$upscope $end
$enddefinitions $end
$comment Show the parameter values. $end
$dumpall
$end
#0
$dumpvars
0%
0$
0#
0"
0!
$end
#1000
1!
1%
#2000
0%
1$
#3000
1"
0!
1%
#4000
0"
1!
0%
0$
1#
#5000
1"
0!
1%
#6000
0%
1$
#7000
1!
1%
